{
	"info": {
		"_postman_id": "e9bc4e65-2326-4cdd-801d-415e0ec65100",
		"name": "Attrecto Academy - NodeJs",
		"schema": "https://schema.getpostman.com/json/collection/v2.1.0/collection.json"
	},
	"item": [
		{
			"name": "localhost:3000/badges",
			"request": {
				"method": "GET",
				"header": [
					{
						"key": "Content-Type",
						"value": "application/json"
					}
				],
				"body": {
					"mode": "raw",
					"raw": ""
				},
				"url": {
					"raw": "localhost:3000/badges",
					"host": [
						"localhost"
					],
					"port": "3000",
					"path": [
						"badges"
					]
				}
			},
			"response": []
		},
		{
			"name": "localhost:3000/badges",
			"request": {
				"method": "POST",
				"header": [
					{
						"key": "Content-Type",
						"value": "application/json"
					}
				],
				"body": {
					"mode": "raw",
					"raw": "{\n\t\"name\": \"Badge X\"\n}"
				},
				"url": {
					"raw": "localhost:3000/badges",
					"host": [
						"localhost"
					],
					"port": "3000",
					"path": [
						"badges"
					]
				}
			},
			"response": []
		},
		{
			"name": "localhost:3000/badges/:id",
			"request": {
				"method": "GET",
				"header": [
					{
						"key": "Content-Type",
						"value": "application/json"
					}
				],
				"body": {
					"mode": "raw",
					"raw": ""
				},
				"url": {
					"raw": "localhost:3000/badges/2",
					"host": [
						"localhost"
					],
					"port": "3000",
					"path": [
						"badges",
						"2"
					]
				}
			},
			"response": []
		},
		{
			"name": "localhost:3000/badges/:id",
			"request": {
				"method": "PATCH",
				"header": [
					{
						"key": "Content-Type",
						"value": "application/json"
					}
				],
				"body": {
					"mode": "raw",
					"raw": "{\n\t\"name\": \"Badge 3\",\n\t\"description\": \"Badge X\"\n}"
				},
				"url": {
					"raw": "localhost:3000/badges/3",
					"host": [
						"localhost"
					],
					"port": "3000",
					"path": [
						"badges",
						"3"
					]
				}
			},
			"response": []
		},
		{
			"name": "localhost:3000/badges/:id",
			"request": {
				"method": "DELETE",
				"header": [
					{
						"key": "Content-Type",
						"value": "application/json"
					}
				],
				"body": {
					"mode": "raw",
					"raw": ""
				},
				"url": {
					"raw": "localhost:3000/badges/3",
					"host": [
						"localhost"
					],
					"port": "3000",
					"path": [
						"badges",
						"3"
					]
				}
			},
			"response": []
		},
		{
			"name": "localhost:3000/users",
			"request": {
				"method": "GET",
				"header": [
					{
						"key": "Content-Type",
						"value": "application/json"
					}
				],
				"body": {
					"mode": "raw",
					"raw": ""
				},
				"url": {
					"raw": "localhost:3000/users",
					"host": [
						"localhost"
					],
					"port": "3000",
					"path": [
						"users"
					]
				}
			},
			"response": []
		},
		{
			"name": "localhost:3000/users",
			"request": {
				"method": "POST",
				"header": [
					{
						"key": "Content-Type",
						"value": "application/json"
					}
				],
				"body": {
					"mode": "raw",
					"raw": "{\n\t\"name\": \"User X\"\n}"
				},
				"url": {
					"raw": "localhost:3000/users",
					"host": [
						"localhost"
					],
					"port": "3000",
					"path": [
						"users"
					]
				}
			},
			"response": []
		},
		{
			"name": "localhost:3000/users/:id",
			"request": {
				"method": "GET",
				"header": [
					{
						"key": "Content-Type",
						"value": "application/json"
					}
				],
				"body": {
					"mode": "raw",
					"raw": ""
				},
				"url": {
					"raw": "localhost:3000/users/2",
					"host": [
						"localhost"
					],
					"port": "3000",
					"path": [
						"users",
						"2"
					]
				}
			},
			"response": []
		},
		{
			"name": "localhost:3000/users/:id",
			"request": {
				"method": "PATCH",
				"header": [
					{
						"key": "Content-Type",
						"value": "application/json"
					}
				],
				"body": {
					"mode": "raw",
					"raw": "{\n\t\"name\": \"User Z\"\n}"
				},
				"url": {
					"raw": "localhost:3000/users/2",
					"host": [
						"localhost"
					],
					"port": "3000",
					"path": [
						"users",
						"2"
					]
				}
			},
			"response": []
		},
		{
			"name": "localhost:3000/users/:id",
			"request": {
				"method": "DELETE",
				"header": [
					{
						"key": "Content-Type",
						"value": "application/json"
					}
				],
				"body": {
					"mode": "raw",
					"raw": ""
				},
				"url": {
					"raw": "localhost:3000/users/2",
					"host": [
						"localhost"
					],
					"port": "3000",
					"path": [
						"users",
						"2"
					]
				}
			},
			"response": []
		},
		{
			"name": "localhost:3000/users/:userId/badges",
			"request": {
				"method": "GET",
				"header": [
					{
						"key": "Content-Type",
						"value": "application/json"
					}
				],
				"body": {
					"mode": "raw",
					"raw": ""
				},
				"url": {
					"raw": "localhost:3000/users/3/badges",
					"host": [
						"localhost"
					],
					"port": "3000",
					"path": [
						"users",
						"3",
						"badges"
					]
				}
			},
			"response": []
		},
		{
			"name": "localhost:3000/users/:userId/badges/:badgeId",
			"request": {
				"method": "GET",
				"header": [
					{
						"key": "Content-Type",
						"value": "application/json"
					}
				],
				"body": {
					"mode": "raw",
					"raw": ""
				},
				"url": {
					"raw": "localhost:3000/users/2/badges/1",
					"host": [
						"localhost"
					],
					"port": "3000",
					"path": [
						"users",
						"2",
						"badges",
						"1"
					]
				}
			},
			"response": []
		},
		{
			"name": "localhost:3000/users/:userId/badges/:badgeId",
			"request": {
				"method": "POST",
				"header": [
					{
						"key": "Content-Type",
						"value": "application/json"
					}
				],
				"body": {
					"mode": "raw",
					"raw": "{\n\n}"
				},
				"url": {
					"raw": "localhost:3000/users/1/badges/1",
					"host": [
						"localhost"
					],
					"port": "3000",
					"path": [
						"users",
						"1",
						"badges",
						"1"
					]
				}
			},
			"response": []
		},
		{
			"name": "localhost:3000/users/:userId/badges/:badgeId",
			"request": {
				"method": "DELETE",
				"header": [
					{
						"key": "Content-Type",
						"value": "application/json"
					}
				],
				"body": {
					"mode": "raw",
					"raw": ""
				},
				"url": {
					"raw": "localhost:3000/users/1/badges/1",
					"host": [
						"localhost"
					],
					"port": "3000",
					"path": [
						"users",
						"1",
						"badges",
						"1"
					]
				}
			},
			"response": []
		}
	]
}